MANIFEST.in
README.md
setup.cfg
setup.py
melee/__init__.py
melee/actiondata.csv
melee/characterdata.csv
melee/console.py
melee/controller.py
melee/enums.py
melee/framedata.csv
melee/framedata.py
melee/gamestate.py
melee/logger.py
melee/menuhelper.py
melee/slippstream.py
melee/slpfilestreamer.py
melee/stages.py
melee/techskill.py
melee/version.py
melee.egg-info/PKG-INFO
melee.egg-info/SOURCES.txt
melee.egg-info/dependency_links.txt
melee.egg-info/requires.txt
melee.egg-info/top_level.txt