Metadata-Version: 1.1
Name: melee
Version: 0.21.1
Summary: Open API written in Python 3 for making your own Smash Bros: Melee AI that works with Slippi Online
Home-page: https://github.com/altf4/libmelee
Author: AltF4
Author-email: altf4petro@gmail.com
License: LGPLv3
Download-URL: https://api.github.com/repos/libmelee/libmelee/tarball
Keywords: dolphin,AI,video games,melee,smash bros,slippi
Platform: UNKNOWN
